pesim/__init__.py
pesim/define.cp39-win_amd64.pyd
pesim/define.pxd
pesim/event.cp39-win_amd64.pyd
pesim/event.pxd
pesim/lock.cp39-win_amd64.pyd
pesim/lock.pxd
pesim/math_aux.cp39-win_amd64.pyd
pesim/math_aux.pxd
pesim/pairing_heap.cp39-win_amd64.pyd
pesim/pairing_heap.pxd
pesim/process.cp39-win_amd64.pyd
pesim/process.pxd
pesim/sim.cp39-win_amd64.pyd
pesim/sim.pxd
pesim-0.9.5.0.dist-info/LICENSE
pesim-0.9.5.0.dist-info/METADATA
pesim-0.9.5.0.dist-info/WHEEL
pesim-0.9.5.0.dist-info/top_level.txt
pesim-0.9.5.0.dist-info/RECORD
