Metadata-Version: 2.1
Name: pesim
Version: 0.9.5.0
Summary: A Minimalist Discrete Event Simulation Library in Python
Home-page: https://github.com/Tefx/pesim
Author: Tefx
Author-email: zhaomeng.zhu@gmail.com
License: UNKNOWN
Project-URL: Documentation, https://pesim.readthedocs.io
Project-URL: Source Code, https://github.com/Tefx/pesim
Platform: UNKNOWN
Classifier: Programming Language :: Python :: 3
Classifier: Development Status :: 4 - Beta
Classifier: License :: OSI Approved :: GNU Lesser General Public License v3 (LGPLv3)
Classifier: Operating System :: OS Independent
Classifier: Topic :: Scientific/Engineering
